{
  "Projects": [
    {
      "GlobalData": {
        "ProjectId": "16e8c58a-8a13-482f-a509-8a65ea916241",
        "ProjectName": "Test19",
        "DBTypeName": "SQL Server",
        "Environments": [
          {
            "EnvironmentId": "d29a45e4-3221-4acf-807b-8251313c0466",
            "EnvironmentName": "Dev_Env_1",
            "EnvironmentType": "DEV",
            "Databases": [
              {
                "DatabaseId": "77553164-2cba-4e9e-bb13-4e85ed7b73f4",
                "DatabaseAliasName": "WWI",
                "DatabaseConnectionDetails": {
                  "DBTypeName": "SQL Server",
                  "Host": "LAPTOP-FUME900I",
                  "AuthenticationType": 1,
                  "Username": "sa",
                  "Password": "123456",
                  "DatabaseName": "WideWorldImporters"
                },
                "RepositoryDetails": {
                  "$type": "DOP.SourceControl.ExternalSourceControl.Git.Models.GitRepositoryDetails, DOP.SourceControl.ExternalSourceControl.Git",
                  "RemoteRepositoryURL": "https://github.com/Condensator/wwi.git",
                  "BranchName": "master"
                }
              }
            ]
          }
        ],
        "SourceControlPathType": 0,
        "Configuration": {
          "BuildMigrationScriptAutomatically": true,
          "BuildMethod": 1,
          "NumberOfRevisionsInViewHistory": 10,
          "NumberOfTagsInBuildOptions": 10,
          "BuildDeploymentScriptOnPush": false,
          "PreventCommitObjectWithConflict": false
        },
        "ProjectArchitecture": 0,
        "LocalDirectory": "C:\\SCA\\Tests\\Test19"
      },
      "UserData": [
        {
          "UserName": "Condensator",
          "DatabasesData": [
            {
              "DatabaseId": "77553164-2cba-4e9e-bb13-4e85ed7b73f4",
              "DatabaseAliasName": "WWI",
              "DatabaseConnectionDetails": {
                "DBTypeName": "SQL Server",
                "Host": "LAPTOP-FUME900I",
                "AuthenticationType": 1,
                "Username": "sa",
                "Password": "123456",
                "DatabaseName": "WideWorldImporters"
              },
              "RepositoryCredentials": {
                "UserName": "Condensator",
                "Password": "H6Gte/7nRWsdJD2JJdlSUYyjMmmls20UatW2yTiPZ+53Yyq6oHEURULCnlYxnXEP"
              }
            }
          ]
        },
        {
          "UserName": "jsmith19870",
          "DatabasesData": [
            {
              "DatabaseId": "77553164-2cba-4e9e-bb13-4e85ed7b73f4",
              "DatabaseAliasName": "WWI",
              "DatabaseConnectionDetails": {
                "DBTypeName": "SQL Server",
                "Host": "LAPTOP-FUME900I",
                "AuthenticationType": 1,
                "Username": "sa",
                "Password": "123456",
                "DatabaseName": "WorldWideImporters2"
              },
              "RepositoryCredentials": {
                "UserName": "jsmith19870",
                "Password": "Z7Z0xNUPw009qb4+cY0rjzTeC/jx/etNk/0bYy7n/JAzakVkqP+/pE5yslqjbIKn"
              }
            }
          ]
        }
      ]
    },
    {
      "GlobalData": {
        "ProjectId": "7b7e7813-5156-42d3-9751-5c93567ad112",
        "ProjectName": "Test20",
        "DBTypeName": "SQL Server",
        "Environments": [
          {
            "EnvironmentId": "011688b1-7074-4907-b236-ebbaf5fee9d9",
            "EnvironmentName": "Dev_Env_1",
            "EnvironmentType": "DEV",
            "Databases": [
              {
                "DatabaseId": "a4d3c7c3-88a1-4a58-b235-f18ab7d6e94e",
                "DatabaseAliasName": "AWDW2019",
                "DatabaseConnectionDetails": {
                  "DBTypeName": "SQL Server",
                  "Host": "LAPTOP-FUME900I",
                  "AuthenticationType": 1,
                  "Username": "sa",
                  "Password": "qrE4JauJd0gM7CQ0IggpFA==",
                  "DatabaseName": "AdventureWorksDW2019"
                },
                "RepositoryDetails": {
                  "$type": "DOP.SourceControl.ExternalSourceControl.Git.Models.GitRepositoryDetails, DOP.SourceControl.ExternalSourceControl.Git",
                  "RemoteRepositoryURL": "https://github.com/Condensator/shredarcitecture.git",
                  "BranchName": "master"
                }
              }
            ]
          }
        ],
        "SourceControlPathType": 0,
        "Configuration": {
          "BuildMigrationScriptAutomatically": true,
          "BuildMethod": 1,
          "NumberOfRevisionsInViewHistory": 10,
          "NumberOfTagsInBuildOptions": 10,
          "BuildDeploymentScriptOnPush": false,
          "PreventCommitObjectWithConflict": false
        },
        "ProjectArchitecture": 1,
        "LocalDirectory": "C:\\SCA\\Tests\\Test20"
      },
      "UserData": [
        {
          "UserName": "Condensator",
          "DatabasesData": [
            {
              "DatabaseId": "a4d3c7c3-88a1-4a58-b235-f18ab7d6e94e",
              "DatabaseAliasName": "AWDW2019",
              "DatabaseConnectionDetails": null,
              "RepositoryCredentials": {
                "UserName": "Condensator",
                "Password": "H6Gte/7nRWsdJD2JJdlSUYyjMmmls20UatW2yTiPZ+53Yyq6oHEURULCnlYxnXEP"
              }
            }
          ]
        },
        {
          "UserName": "jsmith19870",
          "DatabasesData": [
            {
              "DatabaseId": "a4d3c7c3-88a1-4a58-b235-f18ab7d6e94e",
              "DatabaseAliasName": "AWDW2019",
              "DatabaseConnectionDetails": null,
              "RepositoryCredentials": {
                "UserName": "jsmith19870",
                "Password": "Z7Z0xNUPw009qb4+cY0rjzTeC/jx/etNk/0bYy7n/JAzakVkqP+/pE5yslqjbIKn"
              }
            }
          ]
        }
      ]
    },
    {
      "GlobalData": {
        "ProjectId": "3c2d7c46-c692-46b8-93bd-1aefc5b57b10",
        "ProjectName": "Test21",
        "DBTypeName": "SQL Server",
        "Environments": [
          {
            "EnvironmentId": "138ae2ea-bc9c-4f3c-9457-912be48ccca3",
            "EnvironmentName": "Dev_Env_1",
            "EnvironmentType": "DEV",
            "Databases": [
              {
                "DatabaseId": "85492bbb-3be8-4559-8bcd-8ee863cf0a40",
                "DatabaseAliasName": "BigDB",
                "DatabaseConnectionDetails": {
                  "DBTypeName": "SQL Server",
                  "Host": "LAPTOP-FUME900I",
                  "AuthenticationType": 1,
                  "Username": "sa",
                  "Password": "123456",
                  "DatabaseName": "abigdb2"
                },
                "RepositoryDetails": {
                  "$type": "DOP.SourceControl.ExternalSourceControl.Git.Models.GitRepositoryDetails, DOP.SourceControl.ExternalSourceControl.Git",
                  "RemoteRepositoryURL": "https://github.com/Condensator/BigDB.git",
                  "BranchName": "master"
                }
              }
            ]
          }
        ],
        "SourceControlPathType": 0,
        "Configuration": {
          "BuildMigrationScriptAutomatically": true,
          "BuildMethod": 1,
          "NumberOfRevisionsInViewHistory": 10,
          "NumberOfTagsInBuildOptions": 10,
          "BuildDeploymentScriptOnPush": false,
          "PreventCommitObjectWithConflict": false
        },
        "ProjectArchitecture": 0,
        "LocalDirectory": "C:\\SCA\\Tests\\Test21"
      },
      "UserData": [
        {
          "UserName": "jsmith19870",
          "DatabasesData": [
            {
              "DatabaseId": "85492bbb-3be8-4559-8bcd-8ee863cf0a40",
              "DatabaseAliasName": "BigDB",
              "DatabaseConnectionDetails": {
                "DBTypeName": "SQL Server",
                "Host": "LAPTOP-FUME900I",
                "AuthenticationType": 1,
                "Username": "sa",
                "Password": "qrE4JauJd0gM7CQ0IggpFA==",
                "DatabaseName": "abigdb1"
              },
              "RepositoryCredentials": {
                "UserName": "jsmith19870",
                "Password": "Z7Z0xNUPw009qb4+cY0rjzTeC/jx/etNk/0bYy7n/JAzakVkqP+/pE5yslqjbIKn"
              }
            }
          ]
        },
        {
          "UserName": "Condensator",
          "DatabasesData": [
            {
              "DatabaseId": "85492bbb-3be8-4559-8bcd-8ee863cf0a40",
              "DatabaseAliasName": "BigDB",
              "DatabaseConnectionDetails": {
                "DBTypeName": "SQL Server",
                "Host": "LAPTOP-FUME900I",
                "AuthenticationType": 1,
                "Username": "sa",
                "Password": "123456",
                "DatabaseName": "abigdb2"
              },
              "RepositoryCredentials": {
                "UserName": "Condensator",
                "Password": "H6Gte/7nRWsdJD2JJdlSUYyjMmmls20UatW2yTiPZ+53Yyq6oHEURULCnlYxnXEP"
              }
            }
          ]
        }
      ]
    },
    {
      "GlobalData": {
        "ProjectId": "b4ccf242-32aa-4946-b091-7f79795fec79",
        "ProjectName": "Test23",
        "DBTypeName": "SQL Server",
        "Environments": null,
        "SourceControlPathType": 0,
        "Configuration": {
          "BuildMigrationScriptAutomatically": true,
          "BuildMethod": 1,
          "NumberOfRevisionsInViewHistory": 10,
          "NumberOfTagsInBuildOptions": 10,
          "BuildDeploymentScriptOnPush": false,
          "PreventCommitObjectWithConflict": false
        },
        "ProjectArchitecture": 0,
        "LocalDirectory": "C:\\Users\\Oleksandr Kosenko\\Documents\\Test23"
      },
      "UserData": [
        {
          "UserName": "Condensator",
          "DatabasesData": []
        }
      ]
    }
  ],
  "GlobalConfigurations": null
}